Metadata-Version: 1.0
Name: stats-distribution
Version: 0.1
Summary: Gaussian distributions
Home-page: UNKNOWN
Author: Ajinkya Joshi
Author-email: ajinkya.dj92@gmail.com
License: UNKNOWN
Platform: UNKNOWN
